{"frames":[{"x":426,"y":240,"angle":"-36.00","scaleX":"0.0000","scaleY":"0.0000"},{"x":426,"y":240,"angle":"-34.88","scaleX":"0.0305","scaleY":"0.0305"},{"x":426,"y":240,"angle":"-33.73","scaleX":"0.0619","scaleY":"0.0619"},{"x":426,"y":240,"angle":"-32.54","scaleX":"0.0942","scaleY":"0.0942"},{"x":426,"y":240,"angle":"-31.33","scaleX":"0.1272","scaleY":"0.1272"},{"x":426,"y":240,"angle":"-30.09","scaleX":"0.1609","scaleY":"0.1609"},{"x":426,"y":240,"angle":"-28.83","scaleX":"0.1953","scaleY":"0.1953"},{"x":426,"y":240,"angle":"-27.54","scaleX":"0.2302","scaleY":"0.2302"},{"x":426,"y":240,"angle":"-26.24","scaleX":"0.2656","scaleY":"0.2656"},{"x":426,"y":240,"angle":"-24.92","scaleX":"0.3014","scaleY":"0.3014"},{"x":426,"y":240,"angle":"-23.59","scaleX":"0.3375","scaleY":"0.3375"},{"x":426,"y":240,"angle":"-22.26","scaleX":"0.3739","scaleY":"0.3739"},{"x":426,"y":240,"angle":"-20.91","scaleX":"0.4104","scaleY":"0.4104"},{"x":426,"y":240,"angle":"-19.56","scaleX":"0.4470","scaleY":"0.4470"},{"x":426,"y":240,"angle":"-18.21","scaleX":"0.4837","scaleY":"0.4837"},{"x":426,"y":240,"angle":"-16.86","scaleX":"0.5203","scaleY":"0.5203"},{"x":426,"y":240,"angle":"-15.52","scaleX":"0.5568","scaleY":"0.5568"},{"x":426,"y":240,"angle":"-14.18","scaleX":"0.5931","scaleY":"0.5931"},{"x":426,"y":240,"angle":"-12.86","scaleX":"0.6291","scaleY":"0.6291"},{"x":426,"y":240,"angle":"-11.55","scaleX":"0.6648","scaleY":"0.6648"},{"x":426,"y":240,"angle":"-10.25","scaleX":"0.7000","scaleY":"0.7000"},{"x":426,"y":240,"angle":"-8.97","scaleX":"0.7347","scaleY":"0.7347"},{"x":426,"y":240,"angle":"-7.72","scaleX":"0.7689","scaleY":"0.7689"},{"x":426,"y":240,"angle":"-6.48","scaleX":"0.8024","scaleY":"0.8024"},{"x":426,"y":240,"angle":"-5.28","scaleX":"0.8352","scaleY":"0.8352"},{"x":426,"y":240,"angle":"-4.11","scaleX":"0.8672","scaleY":"0.8672"},{"x":426,"y":240,"angle":"-2.96","scaleX":"0.8983","scaleY":"0.8983"},{"x":426,"y":240,"angle":"-1.86","scaleX":"0.9285","scaleY":"0.9285"},{"x":426,"y":240,"angle":"-0.79","scaleX":"0.9576","scaleY":"0.9576"},{"x":426,"y":240,"angle":"-359.76","scaleX":"0.9856","scaleY":"0.9856"},{"x":426,"y":240,"angle":"-358.78","scaleX":"1.0125","scaleY":"1.0125"},{"x":426,"y":240,"angle":"-357.85","scaleX":"1.0381","scaleY":"1.0381"},{"x":426,"y":240,"angle":"-356.96","scaleX":"1.0624","scaleY":"1.0624"},{"x":426,"y":240,"angle":"-356.13","scaleX":"1.0853","scaleY":"1.0853"},{"x":426,"y":240,"angle":"-355.35","scaleX":"1.1067","scaleY":"1.1067"},{"x":426,"y":240,"angle":"-354.63","scaleX":"1.1266","scaleY":"1.1266"},{"x":426,"y":240,"angle":"-353.97","scaleX":"1.1448","scaleY":"1.1448"},{"x":426,"y":240,"angle":"-353.37","scaleX":"1.1613","scaleY":"1.1613"},{"x":426,"y":240,"angle":"-352.85","scaleX":"1.1761","scaleY":"1.1761"},{"x":426,"y":240,"angle":"-352.39","scaleX":"1.1890","scaleY":"1.1890"},{"x":426,"y":240,"angle":"-352.00","scaleX":"1.2000","scaleY":"1.2000"},{"x":426,"y":240,"angle":"-351.73","scaleX":"1.2078","scaleY":"1.2078"},{"x":426,"y":240,"angle":"-351.62","scaleX":"1.2115","scaleY":"1.2115"},{"x":426,"y":240,"angle":"-351.65","scaleX":"1.2114","scaleY":"1.2114"},{"x":426,"y":240,"angle":"-351.81","scaleX":"1.2080","scaleY":"1.2080"},{"x":426,"y":240,"angle":"-352.08","scaleX":"1.2016","scaleY":"1.2016"},{"x":426,"y":240,"angle":"-352.45","scaleX":"1.1925","scaleY":"1.1925"},{"x":426,"y":240,"angle":"-352.90","scaleX":"1.1812","scaleY":"1.1812"},{"x":426,"y":240,"angle":"-353.42","scaleX":"1.1680","scaleY":"1.1680"},{"x":426,"y":240,"angle":"-354.00","scaleX":"1.1533","scaleY":"1.1533"},{"x":426,"y":240,"angle":"-354.63","scaleX":"1.1375","scaleY":"1.1375"},{"x":426,"y":240,"angle":"-355.27","scaleX":"1.1209","scaleY":"1.1209"},{"x":426,"y":240,"angle":"-355.94","scaleX":"1.1040","scaleY":"1.1040"},{"x":426,"y":240,"angle":"-356.60","scaleX":"1.0871","scaleY":"1.0871"},{"x":426,"y":240,"angle":"-357.24","scaleX":"1.0705","scaleY":"1.0705"},{"x":426,"y":240,"angle":"-357.86","scaleX":"1.0547","scaleY":"1.0547"},{"x":426,"y":240,"angle":"-358.43","scaleX":"1.0400","scaleY":"1.0400"},{"x":426,"y":240,"angle":"-358.95","scaleX":"1.0268","scaleY":"1.0268"},{"x":426,"y":240,"angle":"-359.39","scaleX":"1.0155","scaleY":"1.0155"},{"x":426,"y":240,"angle":"-359.74","scaleX":"1.0064","scaleY":"1.0064"},{"x":426,"y":240,"angle":"0.00","scaleX":"1.0000","scaleY":"1.0000"},{"x":426,"y":240,"angle":"-0.19","scaleX":"0.9953","scaleY":"0.9953"},{"x":426,"y":240,"angle":"-0.35","scaleX":"0.9913","scaleY":"0.9913"},{"x":426,"y":240,"angle":"-0.49","scaleX":"0.9879","scaleY":"0.9879"},{"x":426,"y":240,"angle":"-0.60","scaleX":"0.9850","scaleY":"0.9850"},{"x":426,"y":240,"angle":"-0.69","scaleX":"0.9826","scaleY":"0.9826"},{"x":426,"y":240,"angle":"-0.77","scaleX":"0.9808","scaleY":"0.9808"},{"x":426,"y":240,"angle":"-0.82","scaleX":"0.9794","scaleY":"0.9794"},{"x":426,"y":240,"angle":"-0.86","scaleX":"0.9785","scaleY":"0.9785"},{"x":426,"y":240,"angle":"-0.88","scaleX":"0.9780","scaleY":"0.9780"},{"x":426,"y":240,"angle":"-0.89","scaleX":"0.9778","scaleY":"0.9778"},{"x":426,"y":240,"angle":"-0.88","scaleX":"0.9779","scaleY":"0.9779"},{"x":426,"y":240,"angle":"-0.86","scaleX":"0.9784","scaleY":"0.9784"},{"x":426,"y":240,"angle":"-0.83","scaleX":"0.9791","scaleY":"0.9791"},{"x":426,"y":240,"angle":"-0.80","scaleX":"0.9801","scaleY":"0.9801"},{"x":426,"y":240,"angle":"-0.75","scaleX":"0.9813","scaleY":"0.9813"},{"x":426,"y":240,"angle":"-0.70","scaleX":"0.9826","scaleY":"0.9826"},{"x":426,"y":240,"angle":"-0.64","scaleX":"0.9840","scaleY":"0.9840"},{"x":426,"y":240,"angle":"-0.58","scaleX":"0.9856","scaleY":"0.9856"},{"x":426,"y":240,"angle":"-0.51","scaleX":"0.9872","scaleY":"0.9872"},{"x":426,"y":240,"angle":"-0.44","scaleX":"0.9889","scaleY":"0.9889"},{"x":426,"y":240,"angle":"-0.38","scaleX":"0.9906","scaleY":"0.9906"},{"x":426,"y":240,"angle":"-0.31","scaleX":"0.9922","scaleY":"0.9922"},{"x":426,"y":240,"angle":"-0.25","scaleX":"0.9937","scaleY":"0.9937"},{"x":426,"y":240,"angle":"-0.19","scaleX":"0.9952","scaleY":"0.9952"},{"x":426,"y":240,"angle":"-0.14","scaleX":"0.9965","scaleY":"0.9965"},{"x":426,"y":240,"angle":"-0.09","scaleX":"0.9977","scaleY":"0.9977"},{"x":426,"y":240,"angle":"-0.05","scaleX":"0.9987","scaleY":"0.9987"},{"x":426,"y":240,"angle":"-0.02","scaleX":"0.9994","scaleY":"0.9994"},{"x":426,"y":240,"angle":"-0.01","scaleX":"0.9998","scaleY":"0.9998"}]}